{
    "version": "7963.82259533481.786728-iy6jqG3MrBo+EgbO3DrxDg",
    "data": {
        "personalia": {
            "personIdentifikator": {
                "kilde": "system",
                "verdi": "Lorem"
            },
            "navn": {
                "fornavn": "Knut",
                "mellomnavn": "Per",
                "etternavn": "Pedersen",
                "kilde": "system"
            },
            "kontonummer": {
                "kilde": "bruker"
            }
        },
        "arbeid": {},
        "utdanning": {
            "kilde": "utdatert"
        },
        "familie": {
            "forsorgerplikt": {}
        },
        "begrunnelse": {
            "kilde": "bruker",
            "hvorforSoke": "fugiat magna in pariatur",
            "hvaSokesOm": "ut aute ad dolor labore"
        },
        "bosituasjon": {
            "kilde": "utdatert"
        },
        "okonomi": {
            "opplysninger": {
                "utbetaling": [
                    {
                        "kilde": "utdatert",
                        "type": "nostrud esse p",
                        "tittel": "ut cupidatat velit",
                        "overstyrtAvBruker": false
                    },
                    {
                        "kilde": "utdatert",
                        "type": "do eu reprehenderit enim",
                        "tittel": "dolor cupidatat laborum do",
                        "overstyrtAvBruker": true
                    },
                    {
                        "kilde": "bruker",
                        "type": "dolore voluptate et est",
                        "tittel": "Duis consectetur",
                        "overstyrtAvBruker": false
                    },
                    {
                        "kilde": "utdatert",
                        "type": "nulla exercitation anim",
                        "tittel": "commodo ex in",
                        "overstyrtAvBruker": true
                    },
                    {
                        "kilde": "utdatert",
                        "type": "fugiat officia",
                        "tittel": "dolore",
                        "overstyrtAvBruker": false
                    }
                ],
                "utgift": [
                    {
                        "kilde": "utdatert",
                        "type": "voluptate eiusmod est incididunt",
                        "tittel": "veniam dolore aute nostrud",
                        "overstyrtAvBruker": false
                    },
                    {
                        "kilde": "bruker",
                        "type": "ea",
                        "tittel": "ut nostrud adipisicing proident dolore",
                        "overstyrtAvBruker": false
                    },
                    {
                        "kilde": "utdatert",
                        "type": "eiusmod ut laborum",
                        "tittel": "aliquip culpa consectetur",
                        "overstyrtAvBruker": true
                    },
                    {
                        "kilde": "utdatert",
                        "type": "Excepteur dolore",
                        "tittel": "velit ut Lorem",
                        "overstyrtAvBruker": true
                    }
                ]
            },
            "oversikt": {
                "inntekt": [
                    {
                        "kilde": "bruker",
                        "type": "ullamco cupidatat irure",
                        "tittel": "veniam dolore",
                        "overstyrtAvBruker": true
                    },
                    {
                        "kilde": "utdatert",
                        "type": "consequat in laborum exercitation",
                        "tittel": "magna proident mollit tem",
                        "overstyrtAvBruker": false
                    },
                    {
                        "kilde": "utdatert",
                        "type": "minim",
                        "tittel": "aute amet labore do ea",
                        "overstyrtAvBruker": true
                    }
                ],
                "utgift": [
                    {
                        "kilde": "bruker",
                        "type": "nulla",
                        "tittel": "labore laboris in",
                        "overstyrtAvBruker": false
                    },
                    {
                        "kilde": "bruker",
                        "type": "qui",
                        "tittel": "deserunt pariatur irure cupidatat",
                        "overstyrtAvBruker": false
                    }
                ],
                "formue": [
                    {
                        "kilde": "bruker",
                        "type": "eiusmod aliquip officia minim incididunt",
                        "tittel": "est sint ad",
                        "overstyrtAvBruker": false
                    },
                    {
                        "kilde": "bruker",
                        "type": "occaecat fugiat Ut",
                        "tittel": "est elit culpa",
                        "overstyrtAvBruker": false
                    }
                ]
            }
        }
    },
    "driftsinformasjon": "ut et do velit amet",
    "kompatibilitet": []
}