{
    "version": "050086.3981.1581626",
    "data": {
        "personalia": {
            "personIdentifikator": {
                "kilde": "system",
                "verdi": "dolor in"
            },
            "navn": {
                "fornavn": "Bjørn",
                "mellomnavn": "Per",
                "etternavn": "Kristiansen",
                "kilde": "system"
            },
            "kontonummer": {
                "kilde": "utdatert"
            }
        },
        "arbeid": {},
        "utdanning": {
            "kilde": "bruker"
        },
        "familie": {
            "forsorgerplikt": {}
        },
        "begrunnelse": {
            "kilde": "bruker",
            "hvorforSoke": "ad Duis commodo enim voluptate",
            "hvaSokesOm": "eiusm"
        },
        "bosituasjon": {
            "kilde": "utdatert"
        },
        "okonomi": {
            "opplysninger": {
                "utbetaling": [
                    {
                        "kilde": "bruker",
                        "type": "adipisicing",
                        "tittel": "cillum est",
                        "overstyrtAvBruker": true
                    },
                    {
                        "kilde": "bruker",
                        "type": "deserunt elit aliqua occaecat",
                        "tittel": "ullamco in",
                        "overstyrtAvBruker": false
                    },
                    {
                        "kilde": "bruker",
                        "type": "magna dolor ullamco",
                        "tittel": "anim et",
                        "overstyrtAvBruker": true
                    },
                    {
                        "kilde": "utdatert",
                        "type": "dolore qui",
                        "tittel": "eiusmod",
                        "overstyrtAvBruker": true
                    }
                ],
                "utgift": [
                    {
                        "kilde": "utdatert",
                        "type": "ad ea aute irure sit",
                        "tittel": "fugiat reprehenderit ut",
                        "overstyrtAvBruker": true
                    },
                    {
                        "kilde": "utdatert",
                        "type": "laboris reprehenderit sed",
                        "tittel": "enim commodo ad Lorem",
                        "overstyrtAvBruker": false
                    },
                    {
                        "kilde": "utdatert",
                        "type": "deserunt officia amet laborum",
                        "tittel": "anim deserunt Lorem",
                        "overstyrtAvBruker": true
                    },
                    {
                        "kilde": "utdatert",
                        "type": "ea in",
                        "tittel": "reprehenderit culpa deserunt magna",
                        "overstyrtAvBruker": true
                    }
                ]
            },
            "oversikt": {
                "inntekt": [
                    {
                        "kilde": "bruker",
                        "type": "incididunt labore esse deserunt laborum",
                        "tittel": "ad anim Duis veniam reprehenderit",
                        "overstyrtAvBruker": false
                    },
                    {
                        "kilde": "utdatert",
                        "type": "non dolore",
                        "tittel": "eiusmod in tempor in",
                        "overstyrtAvBruker": true
                    },
                    {
                        "kilde": "bruker",
                        "type": "minim Excepteur anim",
                        "tittel": "officia labore",
                        "overstyrtAvBruker": true
                    }
                ],
                "utgift": [
                    {
                        "kilde": "utdatert",
                        "type": "quis voluptate do ex",
                        "tittel": "enim minim elit id",
                        "overstyrtAvBruker": false
                    },
                    {
                        "kilde": "bruker",
                        "type": "nulla aute anim ea",
                        "tittel": "quis tempo",
                        "overstyrtAvBruker": false
                    }
                ],
                "formue": [
                    {
                        "kilde": "bruker",
                        "type": "officia anim voluptate in",
                        "tittel": "sed labore",
                        "overstyrtAvBruker": true
                    }
                ]
            }
        }
    },
    "driftsinformasjon": "labore exercitation",
    "kompatibilitet": []
}